pydomino/__init__.py
pydomino/__main__.py
pydomino/domino
pydomino/pydomino.py
pydomino/pydomino_cpp.cpython-310-x86_64-linux-gnu.so
pydomino/_deps/onnxruntime-src/lib/libonnxruntime.so
pydomino/_deps/onnxruntime-src/lib/libonnxruntime.so.1.16.3
pydomino/onnx_model/phoneme_transition_model.onnx
pydomino_prebuilt-1.2.0.post2.dist-info/METADATA
pydomino_prebuilt-1.2.0.post2.dist-info/WHEEL
pydomino_prebuilt-1.2.0.post2.dist-info/entry_points.txt
pydomino_prebuilt-1.2.0.post2.dist-info/top_level.txt
pydomino_prebuilt-1.2.0.post2.dist-info/RECORD
pydomino_prebuilt-1.2.0.post2.dist-info/licenses/LICENSE
