Metadata-Version: 2.4
Name: pydomino-prebuilt
Version: 1.2.0.post2
Summary: 16kHz モノラル音声に対して指定した音素をアライメントするライブラリ
Author-email: "DWANGO Co., Ltd." <shun_ueda@dwango.co.jp>
Project-URL: Homepage, https://github.com/tsukumijima/pydomino-prebuilt
Project-URL: Repository, https://github.com/tsukumijima/pydomino-prebuilt
Project-URL: Documentation, https://dwangomediavillage.github.io/pydomino/
Classifier: Operating System :: POSIX
Classifier: Operating System :: Unix
Classifier: Operating System :: MacOS
Classifier: Operating System :: Microsoft :: Windows
Classifier: Programming Language :: Python
Classifier: Programming Language :: Python :: 3
Classifier: Programming Language :: Python :: 3.10
Classifier: Programming Language :: Python :: 3.11
Classifier: Programming Language :: Python :: 3.12
Classifier: Programming Language :: Python :: 3.13
Classifier: License :: OSI Approved :: MIT License
Classifier: Topic :: Scientific/Engineering
Classifier: Topic :: Software Development
Classifier: Intended Audience :: Science/Research
Classifier: Intended Audience :: Developers
Requires-Python: >=3.10
License-File: LICENSE
Dynamic: license-file
